azext_resourcegraph/__init__.py
azext_resourcegraph/_client_factory.py
azext_resourcegraph/_help.py
azext_resourcegraph/_params.py
azext_resourcegraph/_validators.py
azext_resourcegraph/azext_metadata.json
azext_resourcegraph/commands.py
azext_resourcegraph/custom.py
azext_resourcegraph/tests/__init__.py
azext_resourcegraph/tests/latest/__init__.py
azext_resourcegraph/tests/latest/test_resourcegraph_commands.py
azext_resourcegraph/vendored_sdks/__init__.py
azext_resourcegraph/vendored_sdks/resourcegraph/__init__.py
azext_resourcegraph/vendored_sdks/resourcegraph/_configuration.py
azext_resourcegraph/vendored_sdks/resourcegraph/_resource_graph_client.py
azext_resourcegraph/vendored_sdks/resourcegraph/_version.py
azext_resourcegraph/vendored_sdks/resourcegraph/aio/__init__.py
azext_resourcegraph/vendored_sdks/resourcegraph/aio/_configuration.py
azext_resourcegraph/vendored_sdks/resourcegraph/aio/_resource_graph_client.py
azext_resourcegraph/vendored_sdks/resourcegraph/aio/operations/__init__.py
azext_resourcegraph/vendored_sdks/resourcegraph/aio/operations/_operations.py
azext_resourcegraph/vendored_sdks/resourcegraph/aio/operations/_resource_graph_client_operations.py
azext_resourcegraph/vendored_sdks/resourcegraph/models/__init__.py
azext_resourcegraph/vendored_sdks/resourcegraph/models/_models.py
azext_resourcegraph/vendored_sdks/resourcegraph/models/_models_py3.py
azext_resourcegraph/vendored_sdks/resourcegraph/models/_resource_graph_client_enums.py
azext_resourcegraph/vendored_sdks/resourcegraph/operations/__init__.py
azext_resourcegraph/vendored_sdks/resourcegraph/operations/_operations.py
azext_resourcegraph/vendored_sdks/resourcegraph/operations/_resource_graph_client_operations.py
resource_graph-2.0.0.dist-info/METADATA
resource_graph-2.0.0.dist-info/WHEEL
resource_graph-2.0.0.dist-info/top_level.txt
resource_graph-2.0.0.dist-info/RECORD
